{
  "updated": "2026-05-08 11:07 IST",
  "timestamp": "2026-05-08T05:37:09.003Z",
  "source": "Metals.dev (MCX INR/g)",
  "items": [
    {
      "key": "gold_14k_basic",
      "label": "14 K GOLD BASIC PRICE (GST & MAKING EXTRA)",
      "unit": "10 g",
      "buy": 89189.92,
      "sell": 89189.92
    },
    {
      "key": "gold_18k_basic",
      "label": "18 K GOLD BASIC PRICE (GST & MAKING EXTRA)",
      "unit": "10 g",
      "buy": 114672.75,
      "sell": 114672.75
    },
    {
      "key": "gold_20k_basic",
      "label": "20 K GOLD BASIC PRICE (GST & MAKING EXTRA)",
      "unit": "10 g",
      "buy": 127414.17,
      "sell": 127414.17
    },
    {
      "key": "gold_22k_basic",
      "label": "22 K GOLD BASIC PRICE (GST & MAKING EXTRA)",
      "unit": "10 g",
      "buy": 140155.58,
      "sell": 140155.58
    },
    {
      "key": "gold_9k_basic",
      "label": "9 K GOLD BASIC PRICE (GST & MAKING EXTRA)",
      "unit": "10 g",
      "buy": 57336.38,
      "sell": 57336.38
    },
    {
      "key": "gold_99_50_cash",
      "label": "GOLD 99.50 CASH BHAV",
      "unit": "10 g",
      "raw_base": 152132.51,
      "mid": 161260.46,
      "buy": 160857,
      "sell": 161664
    },
    {
      "key": "gold_max",
      "label": "GOLD MAX (MCX GOLD)",
      "unit": "10 g",
      "buy": 152897.00,
      "sell": 152897.00
    },
    {
      "key": "gold_99_50_rtgs",
      "label": "GOLD 99.50 RTGS BHAV",
      "unit": "10 g",
      "raw_base": 152132.52,
      "mid": 158217.82,
      "buy": 157743,
      "sell": 158692
    },
    {
      "key": "silver_999_cash",
      "label": "SILVER 999 SILCUT CASH BHAV",
      "unit": "1 kg",
      "raw_base": 261238.50,
      "mid": 269075.66,
      "buy": 268268,
      "sell": 269883
    },
    {
      "key": "silver_max",
      "label": "SILVER MAX (MCX SILVER)",
      "unit": "1 kg",
      "buy": 261500.00,
      "sell": 261500.00
    },
    {
      "key": "silver_refinery",
      "label": "SILVER REFINERY 99 PLUS CASH BHAV",
      "unit": "1 kg",
      "buy": 258885,
      "sell": 258885
    },
    {
      "key": "silver_999_rtgs",
      "label": "SILVER SILCUT 999 RTGS BHAV",
      "unit": "1 kg",
      "buy": 269345,
      "sell": 269345
    }
  ]
}
